nport/__about__.py
nport/__init__.py
nport/_connector.py
nport/_utils.py
nport/_xmltools.py
nport/download_filings.py
nport/fund.py
nport/instruments.py
nport/report.py
sec_nport-1.0.0.dist-info/METADATA
sec_nport-1.0.0.dist-info/WHEEL
sec_nport-1.0.0.dist-info/licenses/LICENSE
sec_nport-1.0.0.dist-info/RECORD
