Metadata-Version: 2.4
Name: sec-nport
Version: 1.0.0
Summary: Fast and reliable parsing of financial instrument data from N-PORT filings.
Project-URL: Repository, https://github.com/dev-quanty/sec-nport.git
Author: dev-quanty
License:                     GNU GENERAL PUBLIC LICENSE
License-File: LICENSE
Keywords: edgar,filings,finance,financial,nport,python,reports,sec
Classifier: Development Status :: 3 - Alpha
Classifier: Programming Language :: Python :: 3.10
Classifier: Programming Language :: Python :: 3.11
Classifier: Programming Language :: Python :: 3.12
Classifier: Programming Language :: Python :: 3.13
Requires-Python: >=3.10
Requires-Dist: beautifulsoup4>=4.12.3
Requires-Dist: httpx>=0.28.0
Requires-Dist: lxml>=5.3.0
Requires-Dist: orjson>=3.10.0
Requires-Dist: pandas>=2.2.3
Requires-Dist: pydantic>=2.10.0
Requires-Dist: rich>=13.9.4
Requires-Dist: stamina>=24.3.0
Requires-Dist: tqdm>=4.67.0
